easeui/Button.py
easeui/CheckButton.py
easeui/Debug.py
easeui/Entry.py
easeui/Image.py
easeui/Windows.py
easeui/__init__.py
EaseUI-0.2.dist-info/METADATA
EaseUI-0.2.dist-info/WHEEL
EaseUI-0.2.dist-info/top_level.txt
EaseUI-0.2.dist-info/RECORD
