Metadata-Version: 2.1
Name: EaseUI
Version: 0.2
Summary: A Python library for rapid UI prototyping
Home-page: http://github.com/PainDe0Mie/easeui
Author: PainDe0Mie
Author-email: painde0mie@gmail.com
Classifier: License :: OSI Approved :: MIT License
Classifier: Programming Language :: Python :: 3
Classifier: Programming Language :: Python :: 3.9
Requires-Dist: pillow
Requires-Dist: tkhtmlview
Requires-Dist: matplotlib
